{
  "properties": {
    "people": "osborne_saunders",
    "happening": "trapping",
    "impacts": "Damage to gathering grounds",
    "placename": "Enetai Chestnut",
    "today": "2014-01-04",
    "meta": {
      "instanceId": "uuid:8feccc13-fc61-4a06-8f7d-05b586385c12"
    },
    "picture": {
      "url": "https://s3.amazonaws.com/images.digital-democracy.org/mapfilter-sample/sample-3.jpg"
    },
    "area": "Lower Kuyuwini",
    "village": "Zoopo Naawa",
    "region": "Deep South",
    "caption": "In labore sunt"
  },
  "geometry": {
    "coordinates": [
      -59.1744934534654,
      2.89962764820084
    ],
    "type": "Point"
  },
  "type": "Feature"
}